odoo10_addon_account_invoice_fixed_discount-10.0.1.0.0-py2.7-nspkg.pth
odoo/addons/account_invoice_fixed_discount/README.rst
odoo/addons/account_invoice_fixed_discount/__init__.py
odoo/addons/account_invoice_fixed_discount/__manifest__.py
odoo/addons/account_invoice_fixed_discount/models/__init__.py
odoo/addons/account_invoice_fixed_discount/models/account_invoice.py
odoo/addons/account_invoice_fixed_discount/reports/report_account_invoice.xml
odoo/addons/account_invoice_fixed_discount/static/description/icon.png
odoo/addons/account_invoice_fixed_discount/tests/__init__.py
odoo/addons/account_invoice_fixed_discount/tests/test_account_fixed_discount.py
odoo/addons/account_invoice_fixed_discount/views/account_invoice_view.xml
odoo10_addon_account_invoice_fixed_discount-10.0.1.0.0.dist-info/DESCRIPTION.rst
odoo10_addon_account_invoice_fixed_discount-10.0.1.0.0.dist-info/METADATA
odoo10_addon_account_invoice_fixed_discount-10.0.1.0.0.dist-info/RECORD
odoo10_addon_account_invoice_fixed_discount-10.0.1.0.0.dist-info/WHEEL
odoo10_addon_account_invoice_fixed_discount-10.0.1.0.0.dist-info/metadata.json
odoo10_addon_account_invoice_fixed_discount-10.0.1.0.0.dist-info/namespace_packages.txt
odoo10_addon_account_invoice_fixed_discount-10.0.1.0.0.dist-info/top_level.txt
